MANIFEST.in
README.txt
cs.aktak-configure.zcml
setup.py
cs/__init__.py
cs.aktak.egg-info/PKG-INFO
cs.aktak.egg-info/SOURCES.txt
cs.aktak.egg-info/dependency_links.txt
cs.aktak.egg-info/entry_points.txt
cs.aktak.egg-info/namespace_packages.txt
cs.aktak.egg-info/not-zip-safe
cs.aktak.egg-info/paster_plugins.txt
cs.aktak.egg-info/requires.txt
cs.aktak.egg-info/top_level.txt
cs/aktak/__init__.py
cs/aktak/configure.zcml
cs/aktak/profiles.zcml
cs/aktak/rebuild_i18n.sh
cs/aktak/tests.py
cs/aktak/browser/__init__.py
cs/aktak/browser/aktak_summary_view.pt
cs/aktak/browser/aktak_urteka.py
cs/aktak/browser/configure.zcml
cs/aktak/locales/cs.aktak-manual.pot
cs/aktak/locales/cs.aktak.pot
cs/aktak/locales/es/LC_MESSAGES/README.txt
cs/aktak/locales/es/LC_MESSAGES/cs.aktak.po
cs/aktak/locales/eu/LC_MESSAGES/README.txt
cs/aktak/locales/eu/LC_MESSAGES/cs.aktak.po
cs/aktak/profiles/default/metadata.xml
cs/aktak/profiles/default/types/DonEdukia.xml
cs/aktak/profiles/default/types/Folder.xml
docs/HISTORY.txt
docs/INSTALL.txt
docs/LICENSE.GPL
docs/LICENSE.txt