Metadata-Version: 1.1
Name: cs.aktak
Version: 1.2
Summary: An installable theme for Plone 3
Home-page: http://code.codesyntax.com/private
Author: Lur Ibargutxi
Author-email: libargutxi@codesyntax.com
License: GPL
Keywords: web zope plone theme
Platform: UNKNOWN
Classifier: Framework :: Plone
Classifier: Programming Language :: Python
